hydro_snap/__init__.py
hydro_snap/hydrosnap.py
HydroSnap-0.0.1.dist-info/LICENSE
HydroSnap-0.0.1.dist-info/METADATA
HydroSnap-0.0.1.dist-info/WHEEL
HydroSnap-0.0.1.dist-info/top_level.txt
HydroSnap-0.0.1.dist-info/RECORD
